fit_resonator/Sdata.py
fit_resonator/__init__.py
fit_resonator/check_data.py
fit_resonator/fit_multiple.py
fit_resonator/functions.py
fit_resonator/resonator.py
pna_control/__init__.py
pna_control/pna_control.py
pna_control/user.py
pna_control/user_HPsweep.py
pna_control/user_MPsweep.py
pna_control/user_multiple_frequencies.py
pna_control/user_ressearch.py
pna_control/user_widescan.py
temperature_control/__init__.py
temperature_control/pid_control.py
temperature_control/temp_pid_ctrl.py
scresonatorsTEST-2.0.0.dist-info/METADATA
scresonatorsTEST-2.0.0.dist-info/WHEEL
scresonatorsTEST-2.0.0.dist-info/top_level.txt
scresonatorsTEST-2.0.0.dist-info/RECORD
