Metadata-Version: 2.1
Name: scresonatorsTEST
Version: 2.0.0
Summary: Python library for measuring and fitting superconducting resonator data
Home-page: https://github.com/nickkprice/scresonators
Author: Placeholder
Keywords: sample,setuptools,development
Requires-Python: >=3.7
Provides-Extra: dev
Requires-Dist: check-manifest ; extra == 'dev'
Provides-Extra: test
Requires-Dist: coverage ; extra == 'test'
